wsdl2file/__init__.py
wsdl2file/clark.py
wsdl2file/command.py
wsdl2file/const.py
wsdl2file-0.1.dist-info/LICENSE-2.0.txt
wsdl2file-0.1.dist-info/METADATA
wsdl2file-0.1.dist-info/WHEEL
wsdl2file-0.1.dist-info/entry_points.txt
wsdl2file-0.1.dist-info/top_level.txt
wsdl2file-0.1.dist-info/RECORD
