Metadata-Version: 2.1
Name: wsdl2file
Version: 0.1
Summary: Reduce a Web Services Definition (WSDL) down to a single file
Author: Tyler MacDonald
Author-email: Tyler MacDonald <tyler@macdonald.name>
Project-URL: Homepage, https://github.com/proofserve/wsdl2file
Project-URL: Issues, https://github.com/proofserve/wsdl2file/issues
Classifier: Programming Language :: Python :: 3
Classifier: License :: OSI Approved :: Apache Software License
Classifier: Operating System :: OS Independent
Requires-Python: >=3.9
License-File: LICENSE-2.0.txt
Requires-Dist: setuptools
Requires-Dist: requests
Requires-Dist: requests-file
Requires-Dist: lxml
